sassyshell/__init__.py
sassyshell/__main__.py
sassyshell/classifier.py
sassyshell/cli.py
sassyshell/config.py
sassyshell/llm_client.py
sassyshell/setup.py
sassyshell/storage.py
sassyshell-0.1.6.dist-info/licenses/LICENSE
sassyshell-0.1.6.dist-info/METADATA
sassyshell-0.1.6.dist-info/WHEEL
sassyshell-0.1.6.dist-info/entry_points.txt
sassyshell-0.1.6.dist-info/top_level.txt
sassyshell-0.1.6.dist-info/RECORD
