Metadata-Version: 2.4
Name: sassyshell
Version: 0.1.6
Summary: A sassy, AI-powered CLI sidekick that remembers the commands you forget and mocks you into getting better.
Author-email: Parth Jain <parthjain1812@gmail.com>
License-Expression: MIT
Project-URL: Homepage, https://github.com/parthjain18/sassyshell
Project-URL: Issues, https://github.com/parthjain18/sassyshell/issues
Keywords: cli,ai,shell,productivity,developer-tools,linux,terminal
Classifier: Development Status :: 4 - Beta
Classifier: Intended Audience :: Developers
Classifier: Programming Language :: Python :: 3
Classifier: Programming Language :: Python :: 3.12
Classifier: Topic :: Scientific/Engineering :: Artificial Intelligence
Classifier: Topic :: Terminals
Classifier: Topic :: Utilities
Requires-Python: >=3.12
License-File: LICENSE
Requires-Dist: pydantic-settings>=2.11.0
Requires-Dist: scikit-learn>=1.7.2
Requires-Dist: typer>=0.19.2
Requires-Dist: langchain>=0.3.27
Requires-Dist: langchain-ollama>=0.3.10
Requires-Dist: langchain-google-genai>=2.1.12
Requires-Dist: langchain-groq>=0.3.8
Requires-Dist: langchain-openai>=0.3.35
Requires-Dist: langchain-anthropic>=0.3.22
Requires-Dist: grpcio==1.67.1
Dynamic: license-file
